{"name":"build-javascript","namedChunkGroups":{"app":{"name":"app","assets":[{"name":"webpack-runtime-bc88f50e3cba5b889621.js","size":4607},{"name":"framework-234801cefe3e320af8cc.js","size":140340},{"name":"app-86379a040b88a9b07b38.js","size":60979}],"filteredAssets":0,"assetsSize":205926,"filteredAuxiliaryAssets":3,"auxiliaryAssetsSize":593438},"component---src-pages-index-tsx":{"name":"component---src-pages-index-tsx","assets":[{"name":"styles.56e282d612e93ca5bb1d.css","size":547},{"name":"component---src-pages-index-tsx-808d927fe874c86f4e80.js","size":43992}],"filteredAssets":0,"assetsSize":44539,"filteredAuxiliaryAssets":1,"auxiliaryAssetsSize":191100}},"assetsByChunkName":{"app":["webpack-runtime-bc88f50e3cba5b889621.js","framework-234801cefe3e320af8cc.js","app-86379a040b88a9b07b38.js"],"component---src-pages-index-tsx":["styles.56e282d612e93ca5bb1d.css","component---src-pages-index-tsx-808d927fe874c86f4e80.js"]},"childAssetsByChunkName":{}}